beetmon/__init__.py
beetmon/beetmon.py
beetmon-1.0.0.dist-info/METADATA
beetmon-1.0.0.dist-info/WHEEL
beetmon-1.0.0.dist-info/entry_points.txt
beetmon-1.0.0.dist-info/top_level.txt
beetmon-1.0.0.dist-info/RECORD
